mcp_server_notify/__init__.py
mcp_server_notify/__main__.py
mcp_server_notify/schemas.py
mcp_server_notify/server.py
mcp_server_notify/sound.py
mseep_mcp_server_notify-0.1.3.dist-info/METADATA
mseep_mcp_server_notify-0.1.3.dist-info/WHEEL
mseep_mcp_server_notify-0.1.3.dist-info/entry_points.txt
mseep_mcp_server_notify-0.1.3.dist-info/licenses/LICENSE
mseep_mcp_server_notify-0.1.3.dist-info/RECORD
