Metadata-Version: 2.4
Name: mseep-mcp-server-notify
Version: 0.1.3
Summary: MCP Server for system notifications with sound
Author-email: mseep <support@skydeck.ai>
License-File: LICENSE
Requires-Python: >=3.10
Requires-Dist: apprise>=1.9.2
Requires-Dist: mcp[cli]>=1.0.0
Requires-Dist: plyer>=2.0
Requires-Dist: pydantic>=2.0
Requires-Dist: pygame>=2.1; platform_system != 'Windows' and platform_system != 'Darwin'
